y_sweet_sdk/__init__.py
y_sweet_sdk/connection.py
y_sweet_sdk/error.py
y_sweet_sdk/update.py
y_sweet_sdk-0.9.1.dist-info/METADATA
y_sweet_sdk-0.9.1.dist-info/WHEEL
y_sweet_sdk-0.9.1.dist-info/top_level.txt
y_sweet_sdk-0.9.1.dist-info/RECORD
