Metadata-Version: 2.4
Name: y_sweet_sdk
Version: 0.9.1
Summary: Python bindings for the Y-Sweet server
Author-email: Paul Butler <paul@jamsocket.com>
License: MIT
Project-URL: Homepage, https://github.com/jamsocket/y-sweet
Classifier: Programming Language :: Python :: 3
Classifier: License :: OSI Approved :: MIT License
Classifier: Operating System :: OS Independent
Requires-Python: >=3.12
Requires-Dist: requests~=2.32.2
Requires-Dist: pycrdt~=0.9.11
